localvariables/__init__.py
localvariables/demo.py
localvariables_demo_giphy-0.0.6.dist-info/LICENSE
localvariables_demo_giphy-0.0.6.dist-info/METADATA
localvariables_demo_giphy-0.0.6.dist-info/WHEEL
localvariables_demo_giphy-0.0.6.dist-info/entry_points.txt
localvariables_demo_giphy-0.0.6.dist-info/top_level.txt
localvariables_demo_giphy-0.0.6.dist-info/RECORD
