Metadata-Version: 2.1
Name: localvariables-demo-giphy
Version: 0.0.6
Summary: A demo for localvariables
Home-page: UNKNOWN
Author: Michael Barney
Author-email: mbarneyjr5309@gmail.com
License: UNKNOWN
Platform: UNKNOWN
Requires-Dist: giphy-client
